AUTHORS.md
CHANGELOG.md
MANIFEST.in
README.md
setup.py
django_extended_flatpages.egg-info/PKG-INFO
django_extended_flatpages.egg-info/SOURCES.txt
django_extended_flatpages.egg-info/dependency_links.txt
django_extended_flatpages.egg-info/requires.txt
django_extended_flatpages.egg-info/top_level.txt
extended_flatpages/__init__.py
extended_flatpages/admin.py
extended_flatpages/models.py
extended_flatpages/tests.py
extended_flatpages/views.py