Metadata-Version: 1.1
Name: django-extended-flatpages
Version: 0.1
Summary: Django flatpages CKEditor integration and SEO values.
Home-page: https://github.com/hisie/django_extended_flatpages
Author: hisie
Author-email: dcebrian@serincas.com
License: Apache License, Version 2.0
Platform: UNKNOWN
Classifier: Programming Language :: Python
Classifier: License :: OSI Approved :: BSD License
Classifier: Development Status :: 4 - Beta
Classifier: Operating System :: OS Independent
Classifier: Framework :: Django
Classifier: Intended Audience :: Developers
Classifier: Topic :: Internet :: WWW/HTTP :: Dynamic Content
